adon/__init__.py
adon/__main__.py
adon/adon.py
Adon-1.0.2.dist-info/LICENSE
Adon-1.0.2.dist-info/METADATA
Adon-1.0.2.dist-info/WHEEL
Adon-1.0.2.dist-info/entry_points.txt
Adon-1.0.2.dist-info/top_level.txt
Adon-1.0.2.dist-info/RECORD
