Metadata-Version: 2.1
Name: Adon
Version: 1.0.2
Summary: Convert Python objects or JSON files to a compacter format!
Author: PatattMan
License: MIT License
Project-URL: Homepage, https://github.com/ThereAre12Months/Adon
Keywords: JSON,web,Adon
Classifier: License :: OSI Approved :: MIT License
Classifier: Programming Language :: Python
Classifier: Programming Language :: Python :: 3
Requires-Python: >=3.9
License-File: LICENSE
Requires-Dist: tomli ; python_version < "3.11"
